orion/__init__.py
orion/__main__.py
orion/analysis.py
orion/benchmark.py
orion/core.py
orion/data.py
orion/functional.py
orion/progress.py
orion/results.py
orion/utils.py
orion/evaluation/__init__.py
orion/evaluation/common.py
orion/evaluation/contextual.py
orion/evaluation/point.py
orion/evaluation/utils.py
orion/pipelines/pretrained/timesfm/timesfm.json
orion/pipelines/pretrained/timesfm/timesfm_artificialwithanomaly.json
orion/pipelines/pretrained/timesfm/timesfm_msl.json
orion/pipelines/pretrained/timesfm/timesfm_realadexchange.json
orion/pipelines/pretrained/timesfm/timesfm_realawscloudwatch.json
orion/pipelines/pretrained/timesfm/timesfm_realtraffic.json
orion/pipelines/pretrained/timesfm/timesfm_realtweets.json
orion/pipelines/pretrained/timesfm/timesfm_smap.json
orion/pipelines/pretrained/timesfm/timesfm_ucr.json
orion/pipelines/pretrained/timesfm/timesfm_yahooa1.json
orion/pipelines/pretrained/timesfm/timesfm_yahooa2.json
orion/pipelines/pretrained/timesfm/timesfm_yahooa3.json
orion/pipelines/pretrained/timesfm/timesfm_yahooa4.json
orion/pipelines/pretrained/units/units.json
orion/pipelines/pretrained/units/units_artificialwithanomaly.json
orion/pipelines/pretrained/units/units_msl.json
orion/pipelines/pretrained/units/units_realadexchange.json
orion/pipelines/pretrained/units/units_realawscloudwatch.json
orion/pipelines/pretrained/units/units_realtraffic.json
orion/pipelines/pretrained/units/units_realtweets.json
orion/pipelines/pretrained/units/units_smap.json
orion/pipelines/pretrained/units/units_ucr.json
orion/pipelines/pretrained/units/units_yahooa1.json
orion/pipelines/pretrained/units/units_yahooa2.json
orion/pipelines/pretrained/units/units_yahooa3.json
orion/pipelines/pretrained/units/units_yahooa4.json
orion/pipelines/sandbox/anomaly_transformer/anomaly_transformer.json
orion/pipelines/sandbox/anomaly_transformer/anomaly_transformer_artificialwithanomaly.json
orion/pipelines/sandbox/anomaly_transformer/anomaly_transformer_msl.json
orion_ml-0.7.1.dist-info/AUTHORS.rst
orion_ml-0.7.1.dist-info/LICENSE
orion_ml-0.7.1.dist-info/METADATA
orion_ml-0.7.1.dist-info/WHEEL
orion_ml-0.7.1.dist-info/entry_points.txt
orion_ml-0.7.1.dist-info/top_level.txt
orion_ml-0.7.1.dist-info/RECORD
