Metadata-Version: 2.1
Name: orion-ml
Version: 0.7.1
Summary: Orion is a machine learning library built for unsupervised time series anomaly detection.
Home-page: https://github.com/sintel-dev/Orion
Author: MIT Data To AI Lab
Author-email: dailabmit@gmail.com
License: MIT license
Keywords: orion
Classifier: Development Status :: 2 - Pre-Alpha
Classifier: Intended Audience :: Developers
Classifier: License :: OSI Approved :: MIT License
Classifier: Natural Language :: English
Classifier: Programming Language :: Python :: 3
Classifier: Programming Language :: Python :: 3.8
Classifier: Programming Language :: Python :: 3.9
Classifier: Programming Language :: Python :: 3.10
Classifier: Programming Language :: Python :: 3.11
Requires-Python: >=3.8,<3.12
License-File: LICENSE
License-File: AUTHORS.rst
Requires-Dist: tensorflow<2.15,>=2.2
Requires-Dist: numpy<2,>=1.17.5
Requires-Dist: pandas<3,>=1
Requires-Dist: numba<0.60,>=0.48
Requires-Dist: s3fs<0.5,>=0.2.2
Requires-Dist: mlblocks<0.7,>=0.6.2
Requires-Dist: ml-stars<0.4,>=0.2.1.dev0
Requires-Dist: scikit-learn<2,>=0.22.1
Requires-Dist: scipy<1.14
Requires-Dist: tabulate<0.9,>=0.8.3
Requires-Dist: pyts<0.14,>=0.11
Requires-Dist: torch<2.6,>=1.4
Requires-Dist: azure-cognitiveservices-anomalydetector<0.4,>=0.3
Requires-Dist: xlsxwriter<1.4,>=1.3.6
Requires-Dist: tqdm>=4.36.1
Requires-Dist: stumpy<1.11,>=1.7
Requires-Dist: ncps
Requires-Dist: protobuf<4
Provides-Extra: dev
Requires-Dist: pip>=9.0.1; extra == "dev"
Requires-Dist: bumpversion<0.6,>=0.5.3; extra == "dev"
Requires-Dist: watchdog<0.11,>=0.8.3; extra == "dev"
Requires-Dist: docutils<0.18,>=0.12; extra == "dev"
Requires-Dist: m2r2<0.3,>=0.2.5; extra == "dev"
Requires-Dist: nbsphinx<0.7,>=0.5.0; extra == "dev"
Requires-Dist: Sphinx<3.3,>=3; extra == "dev"
Requires-Dist: pydata-sphinx-theme<0.5; extra == "dev"
Requires-Dist: markupsafe<2.1.0; extra == "dev"
Requires-Dist: ipython<9,>=6.5; extra == "dev"
Requires-Dist: Jinja2<3,>=2; extra == "dev"
Requires-Dist: alabaster<=0.7.12; extra == "dev"
Requires-Dist: sphinxcontrib-applehelp<1.0.8; extra == "dev"
Requires-Dist: sphinxcontrib-devhelp<1.0.6; extra == "dev"
Requires-Dist: sphinxcontrib-htmlhelp<2.0.5; extra == "dev"
Requires-Dist: sphinxcontrib-serializinghtml<1.1.10; extra == "dev"
Requires-Dist: sphinxcontrib-qthelp<1.0.7; extra == "dev"
Requires-Dist: flake8<4,>=3.7.7; extra == "dev"
Requires-Dist: isort<5,>=4.3.4; extra == "dev"
Requires-Dist: autoflake<2,>=1.2; extra == "dev"
Requires-Dist: autopep8<2,>=1.4.3; extra == "dev"
Requires-Dist: importlib-metadata<5; extra == "dev"
Requires-Dist: twine<4,>=1.10.0; extra == "dev"
Requires-Dist: wheel>=0.30.0; extra == "dev"
Requires-Dist: coverage<6,>=4.5.1; extra == "dev"
Requires-Dist: tox<4,>=2.9.1; extra == "dev"
Requires-Dist: invoke; extra == "dev"
Requires-Dist: pytest>=3.4.2; extra == "dev"
Requires-Dist: pytest-cov>=2.6.0; extra == "dev"
Requires-Dist: rundoc<0.5,>=0.4.3; extra == "dev"
Provides-Extra: pretrained
Requires-Dist: timm; extra == "pretrained"
Requires-Dist: smart-open; extra == "pretrained"
Requires-Dist: timesfm[torch]<1.5,>=1.2.0; python_version >= "3.11" and extra == "pretrained"
Requires-Dist: jax; python_version >= "3.11" and extra == "pretrained"
Provides-Extra: test
Requires-Dist: pytest>=3.4.2; extra == "test"
Requires-Dist: pytest-cov>=2.6.0; extra == "test"
Requires-Dist: rundoc<0.5,>=0.4.3; extra == "test"
